{"name":"CAR-Q CAPLET","harga":"  Rp. 344.850/ kemasan","golongan":"http://medicastore.com/image_banner/obat_bebas.gif","kandungan":"Co-enzyme Q10 30 mg, L-carnitine fumarat 500 mg.","indikasi":"Melindungi fungsi kardiovaskular & beraksi sebagai antioksidan.","kontraindikasi":"","perhatian":"Kehamilan & menyusui. Interaksi obat: warfarin.","efeksamping":"Gejala pencernaan ringan misal mual, muntah, kram perut & diare.","indeksamanwanitahamil":"","kemasan":"Kaplet salut film 3 x 10 biji","dosis":"3 kapsul sehari.","penyajian":"Dikonsumsi bersamaan dengan makanan","pabrik":"Kalbe Farma.","id":"10428","category_id":"2"}
