{"name":"CAPZACIN CREAM","harga":"  Rp. 53.240/ kemasan","golongan":"http://medicastore.com/image_banner/obat_bebas.gif","kandungan":"Capsaicin.","indikasi":"Perawatan topikal untuk sakit neuropathy diabetic (penyakit syaraf karena diabetes) dan untuk meringankan nyeri akibat osteoarthritis.","kontraindikasi":"Jangan oleskan pada luka yang terbuka.","perhatian":"Jika capzaisin mengenai mata, basuhlah dengan air, jika mengenai area sensitif lainnya cucilah dengan air hangat bersabun.","efeksamping":"Reaksi hipersensitif. Sensasi terbakar dapat muncul selama pemakaian, tapi biasanya hilang dengan penggunaan rutin.","indeksamanwanitahamil":"","kemasan":"Krim 0.075 % x 15 gram x 1's","dosis":"Oleskan krim pada area yang terinfeksi 3-4 kali sehari.","penyajian":"Tak ada pilihan","pabrik":"Combiphar.","id":"10803","category_id":"4"}
