{"name":"SOLAC SYRUP","harga":"  Rp. 87.120/ kemasan","golongan":"http://medicastore.com/image_banner/obat_bebas_terbatas.gif","kandungan":"Laktulosa.","indikasi":"Konstipasi, ensefalopati portal sistemik termasuk keadaan pra-koma hepatik & koma hepatik.","kontraindikasi":"Galaktosemia, obstruksi intestinal.","perhatian":"Kehamilan, diabetes, pemakaian jangka panjang ( > 1 minggu ).","efeksamping":"","indeksamanwanitahamil":"B: Baik penelitian reproduksi hewan tidak menunjukkan risiko pada janin maupun penelitian terkendali pada wanita hamil atau hewan coba tidak memperlihatkan efek merugikan (kecuali penurunan kesuburan) dimana  tidak ada penelitian terkendali yang mengkonfirmasi risiko pada wanita hamil semester pertama (dan tidak ada bukti risiko pada trisemester selanjutnya).","kemasan":"syrup 3.335 g / 5 ml x 120 ml x 1's.","dosis":"Konstipasi Dewasa Kondisi parah: 2 x sehari 15 ml untuk 3 hari pertama, selanjutnya dengan 15-25 ml sehari. Kondisi sedang: 15-30 ml sehari untuk 3 hari pertama, selanjutnya dengan 10-15 ml sehari. Kondisi ringan: 15 ml sehari untuk 3 hari pertama, selanjutnya dengan 10 ml sehari. Anak 5-10 tahun 2 x sehari 10 ml untuk 3 hari pertama, selanjutnya dengan 10 ml sehari, 1-5 tahun 2 x sehari 5 ml untuk 3 hari pertama, selanjutnya dengan 5-10 ml sehari, < 1 tahun 2 x sehari 2.5 ml untuk 3 hari pertama, selanjutnya dengan 5 ml sehari.Pra-koma hepatik & koma hepatik Awal 3 x sehari 30-50 ml.","penyajian":"Dikonsumsi bersamaan dengan makanan","pabrik":"Soho.","id":"11286","category_id":"1"}
