{"name":"CEREBROVIT SENIOR","harga":"  Rp. 13.976/ kemasan","golongan":"http://medicastore.com/image_banner/obat_bebas_terbatas.gif","kandungan":"Ginkgo biloba extr 40 mg, L-glutamic acid 200 mg, thiamine HCL 5 mg, riblofavin HCL 2 mg, pyridoxine HCL 2 mg, Cyanocobalamin 1.5 mcg, niacinamide 5 mg, Ca pantothenate 2 mg, ascorbic acid 25 mg, Fe sebagai Fe sulfate 5 mg, copper 100 mg, Zn 100 mcg, Mg 3.5 mg, Ca 15 mg, fosfor 10 mg, iodine 100 mcg, cobalt 100 mcg, mangan 500 mg, molybdenum 100 mcg.","indikasi":"Suplemen vitamin & mineral untuk meningkatkan stamina.Mencegah penurunan daya ingat, mudah lupa, sulit konsentrasi.","kontraindikasi":"","perhatian":"","efeksamping":"","indeksamanwanitahamil":"","kemasan":"Kapsul 10's.","dosis":"1 kapsul sehari.","penyajian":"","pabrik":"Kalbe Farma.","id":"11850","category_id":"11"}
