{"name":"TROPIDRYL PLUS SYRUP 60 ML","harga":"  Rp. 11.846/ kemasan","golongan":"http://medicastore.com/image_banner/obat_bebas_terbatas.gif","kandungan":"Per 5 ml Diphenhydramine HCl 12.5 mg, dextromethorphan HBr 10 mg, ammoniun Cl 125 mg, natrium sitrat 50 mg, mentol 1 mg.","indikasi":"Ekspektoran & antitusiv untuk meringankan batuk karena pilek atau alergi.","kontraindikasi":"","perhatian":"Penyakit jantung, hipertensi, diabetes, hipertiroid, anak < 2 tahun.","efeksamping":"Mengantuk, pusing, mulut kering, gangguan pencernaan.","indeksamanwanitahamil":"","kemasan":"Sirup 60 ml.","dosis":"Dewasa 2 sendok obat (5 ml) tiap 4-6 jam.Anak 4-11 tahun 1 sendok obat, 2-4 tahun ½ sendok obat.Diberikan tiap 6 jam.","penyajian":"Dikonsumsi bersamaan dengan makanan atau tidak","pabrik":"Tropica Mas Pharma.","id":"12181","category_id":"3"}
