{"name":"LAPIKOT FORTE CAPLET","harga":"  Rp. 157.300/ kemasan","golongan":"http://medicastore.com/image_banner/obat_keras_dan_psikotropika.gif","kandungan":"Co-trimoxazole: Trimethoprim 160 mg, sulfamethoxazole 800 mg.","indikasi":"Infeksi nafas, genitourinary, gastrointestinal & saluran kemih, kulit & telinga, hidung, tenggorokan.","kontraindikasi":"Kerusakan parenkim hatiKerusakan ginjal beratKehamilan","perhatian":"Gangguan hematologi atau fungsi ginjal.","efeksamping":"Gangguan gastrointestinal, Sindrom Stevens Johnson & Lyell's.Jarang hepatitis, gangguan darah, kolitis pseudomembran.","indeksamanwanitahamil":"D: Positif ada kejadian yang berbahaya pada janin manusia, tetapi keuntungan dari penggunaan oleh wanita hamil mungkin dapat diterima walaupun berisiko. (Misalnya jika obat digunakan untuk situasi menyelamatkan nyawa atau penyakit yang serius dimana obat yang lebih aman tidak dapat digunakan atau tidak efektif).","kemasan":"Kaplet 10 x 10's.","dosis":"Dewasa 1 kaplet forte. Anak 6-12 tahun1/4 dosis dewasa. Diberikan 2 x sehari.","penyajian":"Dikonsumsi bersamaan dengan makanan","pabrik":"Lapi Laboratories.","id":"12361","category_id":"7"}
