{"name":"AVAMYS NASAL SPRAY 120'S","harga":"  Rp. 145.200/ kemasan","golongan":"http://medicastore.com/image_banner/obat_keras_dan_psikotropika.gif","kandungan":"Fluticasone furoate","indikasi":"Terapi gejala rhinitis alergi","kontraindikasi":"","perhatian":"","efeksamping":"Epistaxis, ulcer pada hidung","indeksamanwanitahamil":"C: Penelitian pada hewan  menunjukkan efek samping pada janin ( teratogenik atau embriosidal atau lainnya) dan belum ada penelitian yang terkendali pada wanita atau penelitian pada wanita dan hewan belum tersedia. Obat seharusnya diberikan bila hanya keuntungan potensial memberikan alasan terhadap bahaya potensial pada janin.","kemasan":"spray 27,5 mcg/spray x 120 semprot","dosis":"Dewasa & anak >= 12 tahun : Dosis awal 2 semprot pada setiap lubang hidung sekali sehari. Dosis perawatan : 1 semprot pada setiap lubang hidung sekali sehari. Anak usia 6-11 tahun : 1 semprot pada setiap lubang hidung sekali sehari, dapat ditingkatkan menjadi : 2 semprot pada setiap lubang hidung sekali sehari. Dosis perawatan : 1 semprot pada setiap lubang hidung sekali sehari","penyajian":"Tak ada pilihan","pabrik":"GlaxoSmithKline.","id":"12594","category_id":"3"}
