{"name":"ZEVIT GROW CAPLET","harga":"  Rp. 5.967/ kemasan","golongan":"http://medicastore.com/image_banner/obat_bebas.gif","kandungan":"Per caplet : Vit B1 15 mg, vit B2 15 mg, vit B6 20 mg, vit B12 12 mcg, Ca pantothenate 20 mg, nicotinamide 100 mg, vit E 30 mg, vit C 750 mg, copper 2 mg, Zn 2.5 mg.","indikasi":" Membantu memenuhi kebutuhan vitamin B kompleks, vitamin C, vitamin D & mineral pada masa pertumbuhan\r\n Membnatu menjaga daya tahan tubuh","kontraindikasi":"","perhatian":"","efeksamping":"","indeksamanwanitahamil":"","kemasan":"Strip isi 4 caplet","dosis":"Sehari 1-2 kaplet, diminum setelah makan atau sesuai petunjuk dokter","penyajian":"Dikonsumsi bersamaan dengan makanan","pabrik":"Tempo Scan Pacific.","id":"12671","category_id":"11"}
