{"name":"EFRISEL TETES MATA 2,5 % MINIDOSE","harga":"  Rp. 18.604/ kemasan","golongan":"http://medicastore.com/image_banner/obat_keras_dan_psikotropika.gif","kandungan":"Phenylephrine / Fenilefrin HCl.","indikasi":"Midriatikum kerja cepat sebelum operasi atau pemeriksaan oftalmoskopik.","kontraindikasi":"Glaukoma.","perhatian":"Perubahan arteriosklerosis yang jelas, hipertensi yang nyata.","efeksamping":"","indeksamanwanitahamil":"C: Penelitian pada hewan  menunjukkan efek samping pada janin ( teratogenik atau embriosidal atau lainnya) dan belum ada penelitian yang terkendali pada wanita atau penelitian pada wanita dan hewan belum tersedia. Obat seharusnya diberikan bila hanya keuntungan potensial memberikan alasan terhadap bahaya potensial pada janin.","kemasan":"Tetes mata 0,6 ml x 5","dosis":"1 tetes.","penyajian":"Tak ada pilihan","pabrik":"Cendo.","id":"13001","category_id":"13"}
