{"name":"CENDO AUGENTONIC MINIDOSE TETES MATA","harga":"  Rp. 26.166/ kemasan","golongan":"http://medicastore.com/image_banner/obat_bebas_terbatas.gif","kandungan":"Tiap ml larutan mengandung : Vitamin A palmitate 1000 iu; Zinc sulfate 0,2 mg; Phenylephrine HCl 1 mg","indikasi":"Mengatasi iritasi ringan yang disebabkan matahari, angin, debu & asap. Mengurangi gejala lelah pada mata, alergi, inflamasi konjungtiva & photopthalmia, serta gangguan penglihatan karena kelebihan lendir pada mata","kontraindikasi":"Hipersensitif terhadap satu atau lebih kandungan dari obat ini","perhatian":" Hanya untuk pemakaian luar.\r\n Untuk mencegah kontaminasi, hindarkan kontak langsung antara ujung wadah dengan mata.\r\n Untuk menghindari pencemaran, botol harus ditutup kembali setelah pemakaian.\r\n Jangan digunakan jika larutan berubah warna atau keruh.\r\n Jauhkan dari jangkauan anak-anak.\r\n Tidak untuk disuntikkan.\r\n Jangan dipergunakan 3 x 24 jam setelah dibuka","efeksamping":"","indeksamanwanitahamil":"","kemasan":"Cendo augentonic 0,6 ml x 5's","dosis":"3-4 kali sehari 1-2 tetes pada masing-masing mata","penyajian":"Tak ada pilihan","pabrik":"Cendo.","id":"13287","category_id":"13"}
