{"name":"KUTILOS","harga":"  Rp. 20.570/ kemasan","golongan":"http://medicastore.com/image_banner/obat_bebas.gif","kandungan":"Tiap 1 ml mengandung : Asam salisilat 0,2 g; Asam laktat 0,05 g; Polidocanol 0,02 g","indikasi":"Mengatasi kutil, mata ikan & kapalan","kontraindikasi":"","perhatian":"","efeksamping":"","indeksamanwanitahamil":"","kemasan":"Kutilos liquid 10 ml x 1's","dosis":" Bersihkan terlebih dahulu area yang akan diobati dengan air hangat.\r\n Ambil kapas secukupnya. Sesuaikan dengan luas permukaan mata ikan/kutil/kapalan.\r\n Tuangkan Kutilos secukupnya pada kapas, jangan berlebihan.\r\n Tempelkan kapas yang telah dibasahi Kutilos hanya pada area mata ikan/kutil/kapalan.\r\n Kemudian tutuplah dengan plester.\r\n Ulangi penggunaan Kutilos 2 kali sehari, pagi & malam hari.\r\n\r\nBROSUR KUTILOS\r\n\r\n\r\n\r\n\r\n\r\n\r\n","penyajian":"Tak ada pilihan","pabrik":"PT. Etercon Pharma/PT. Novell Pharmaceutical Laboratories","id":"13560","category_id":"15"}
