{"name":"ISONIAZIDE TABLET 100 MG KIMIA FARMA","harga":"  Rp. 15.682/ kemasan","golongan":"http://medicastore.com/image_banner/obat_keras_dan_psikotropika.gif","kandungan":"INH / Isoniazid 100 mg.","indikasi":"Pengobatan semua jenis tuberkulosa dikombinasikan dengan obat anti tuberkulosa lainnya. Dapat digunakan sebagai obat tunggal untuk pencegahan.","kontraindikasi":"Penyakit hati karena obat, penyakit hati akut karena berbagai sebab.","perhatian":"Gangguan fungsi hati dan ginjal.","efeksamping":"Gangguan saluran pencernaan, hipersensitif.","indeksamanwanitahamil":"C: Penelitian pada hewan  menunjukkan efek samping pada janin ( teratogenik atau embriosidal atau lainnya) dan belum ada penelitian yang terkendali pada wanita atau penelitian pada wanita dan hewan belum tersedia. Obat seharusnya diberikan bila hanya keuntungan potensial memberikan alasan terhadap bahaya potensial pada janin.","kemasan":"Tablet 100 mg x 100 biji.","dosis":"Dewasa : 5 mg/kg berat badan atau 300 mg per hari.","penyajian":"Dikonsumsi pada perut kosong (1 atau 2 jam sebelum/sesudah makan)","pabrik":"PT. KIMIA FARMA","id":"2936","category_id":"8"}
