{"name":"ALLORIS TABLET","harga":"  Rp. 487.630/ kemasan","golongan":"http://medicastore.com/image_banner/obat_keras_dan_psikotropika.gif","kandungan":"Loratadine.","indikasi":"Menghilangkan gejala-gejala yang berhubungan dengan rinitis alergi, biduran/kaligata kronis & kelainan kulit yang lain akibat alergi.","kontraindikasi":"","perhatian":"Kehamilan, menyusui.","efeksamping":"","indeksamanwanitahamil":"B: Baik penelitian reproduksi hewan tidak menunjukkan risiko pada janin maupun penelitian terkendali pada wanita hamil atau hewan coba tidak memperlihatkan efek merugikan (kecuali penurunan kesuburan) dimana  tidak ada penelitian terkendali yang mengkonfirmasi risiko pada wanita hamil semester pertama (dan tidak ada bukti risiko pada trisemester selanjutnya).","kemasan":"Tablet 10 mg x 10 x 10's","dosis":"Dewasa & anak berusia 12 tahun ke atas : 1 tablet sehari.","penyajian":"Dikonsumsi bersamaan dengan makanan atau tidak","pabrik":"Sanbe Farma.","id":"317","category_id":"17"}
