{"name":"METHIOSON TABLET","harga":"  Rp. 58.080/ kemasan","golongan":"http://medicastore.com/image_banner/obat_bebas_terbatas.gif","kandungan":"Methionine 100 mg, choline bitartrate 100 mg, vit B1 2 mg, vit B2 2 mg, vit B6 2 mg, vit B12 0.67 mcg, vit E 3 mg, nicotinamide 6 mg, pantothenol 3 mg, biotin 100 mcg, folic acid 400 mcg","indikasi":"Disfungsi hati akibat sakit kuning, infeksi dan subtansi hepatotoksik, pengobatan dengan sinar-x, degenerasi lemak, infiltrasi lemak.Gangguan hati setelah operasi.","kontraindikasi":"","perhatian":"","efeksamping":"","indeksamanwanitahamil":"","kemasan":"Tablet salut gula x 60's","dosis":"3 kali sehari 2-3 tablet.","penyajian":"Dikonsumsi bersamaan dengan makanan","pabrik":"Soho.","id":"3798","category_id":"1"}
