{"name":"OPOX TABLET","harga":"  Rp. 87.120/ kemasan","golongan":"http://medicastore.com/image_banner/obat_keras_dan_psikotropika.gif","kandungan":"Loperamide HCl.","indikasi":"Diare akut dan diare kronis.","kontraindikasi":"Bila hambatan peristaltik dihindari.","perhatian":"Gangguan fungsi hati. Anak berusia kurang dari 12 tahun.","efeksamping":"Kembung, sembelit (susah buang air besar), mual, hipersensitivitas, megakolon, pusing, kelelahan.","indeksamanwanitahamil":"B: Baik penelitian reproduksi hewan tidak menunjukkan risiko pada janin maupun penelitian terkendali pada wanita hamil atau hewan coba tidak memperlihatkan efek merugikan (kecuali penurunan kesuburan) dimana  tidak ada penelitian terkendali yang mengkonfirmasi risiko pada wanita hamil semester pertama (dan tidak ada bukti risiko pada trisemester selanjutnya).","kemasan":"Tablet 2 mg x 10 x 6 biji.","dosis":"Diare akut : awalnya 2 tablet kemudian 1 tablet setiap habis buang air besar. Diare kronis : awalnya 2 tablet kemudian dosis disesuaikan sampai buang air besar normal (buang air besar 1-2 kali sehari). Maksimal 8 tablet sehari.","penyajian":"Dikonsumsi bersamaan dengan makanan atau tidak","pabrik":"Guardian Pharmatama.","id":"4357","category_id":"1"}
