{"name":"PARACETOL ORAL DROPS","harga":"  Rp. 0. Data hanya sebagai informasi","golongan":"http://medicastore.com/image_banner/obat_bebas.gif","kandungan":"Parasetamol / paracetamol","indikasi":"Demam, sakit kepala, myalgia (nyeri otot).","kontraindikasi":"","perhatian":"Gagal ginjal & hati.Interaksi obat : alkohol, antikoagulan oral, Kloramfenikol, Aspirin, Fenobarbital, penginduksi enzim hati, zat-zat yang dapat mengakibatkan hepatotoksis.","efeksamping":"Reaksi kulit, darah, & reaksi alergi lainnya.","indeksamanwanitahamil":"","kemasan":"Tetes 100 mg/mL x 15 mL.","dosis":"Anak berusia 6-12 tahun : 2,4-4,8 ml tiap 4 jam. Anak berusia 2-6 tahun : 1,2-2,4 ml tiap 4 jam. Anak berusia 1-2 tahun : 0,9-1,2 ml tiap 4 jam. Anak berusia 6-12 bulan : 0,6-0,9 ml tiap 4 jam. Anak berusia 1-6 bulan : 0,3-0,6 ml tiap 4 jam.","penyajian":"Dikonsumsi bersamaan dengan makanan atau tidak","pabrik":"Prafa.","id":"4522","category_id":"4"}
