{"name":"PIRALEN SYRUP","harga":"  Rp. 10.285/ kemasan","golongan":"http://medicastore.com/image_banner/obat_keras_dan_psikotropika.gif","kandungan":"Metoclopramide / MetoklopramidaHCl","indikasi":"Mual, muntah, mual dan muntah yang disebabkan oleh intoleransi terhadap obat-obat tertentu.","kontraindikasi":"Trimester pertama kehamilan.","perhatian":"Pasien yang mengkonsumsi obat-obat lain yang dapat menyebabkan reaksi ekstrapiramidal.Gangguan ginjal. Anak-anak dan lanjut usia.","efeksamping":"Sembelit/susah buang air besar, diare, pusing, rasa ngantuk.","indeksamanwanitahamil":"B: Baik penelitian reproduksi hewan tidak menunjukkan risiko pada janin maupun penelitian terkendali pada wanita hamil atau hewan coba tidak memperlihatkan efek merugikan (kecuali penurunan kesuburan) dimana  tidak ada penelitian terkendali yang mengkonfirmasi risiko pada wanita hamil semester pertama (dan tidak ada bukti risiko pada trisemester selanjutnya).","kemasan":"Sirup 5 mg/5 ml x 60 ml.","dosis":"Dewasa : 3 kali sehari 1-2 sendok teh. Anak-anak : 0,5 mg/kg berat badan/hari dalam dosis terbagi.","penyajian":"Dikonsumsi pada perut kosong (1 atau 2 jam sebelum/sesudah makan)","pabrik":"Otto Pharmacetical Laboratories.","id":"4665","category_id":"1"}
