{"name":"ROVAMYCINE TABLET 1,5 MIU","harga":"  Rp. 1.021.004/ kemasan","golongan":"http://medicastore.com/image_banner/obat_keras_dan_psikotropika.gif","kandungan":"Spiramycin / Spiramisin.","indikasi":"Tonsilitis (radang tonsil/amandel), faringitis (radang tekak), otitis media (radang rongga gendang telinga), sinusitis (radang rongga paranasal), & infeksi saluran pernafasan lainnya.","kontraindikasi":"Hipersensitivitas.","perhatian":"Menyusui.","efeksamping":"Gangguan saluran percernaan.Jarang : reaksi alergi kulit, parestesia (gangguan perasaan kulit seperti kesemutan).","indeksamanwanitahamil":"C: Penelitian pada hewan  menunjukkan efek samping pada janin ( teratogenik atau embriosidal atau lainnya) dan belum ada penelitian yang terkendali pada wanita atau penelitian pada wanita dan hewan belum tersedia. Obat seharusnya diberikan bila hanya keuntungan potensial memberikan alasan terhadap bahaya potensial pada janin.","kemasan":"Tablet 1.5 MIU x 100's","dosis":"Dewasa : 3 kali sehari 1 tablet selama 5 hari.","penyajian":"Dikonsumsi bersamaan dengan makanan atau tidak","pabrik":"Sanofi-Aventis.","id":"5305","category_id":"7"}
