{"name":"RHINATHIOL CAPSULE","harga":"  Rp. 254.100/ kemasan","golongan":"http://medicastore.com/image_banner/obat_keras_dan_psikotropika.gif","kandungan":"Carbocisteine / Karbosistein.","indikasi":"Mukolitik (pengencer dahak) untuk bronkhitis akut dan kronis, bronkhiektasis, infeksi sinus, laringitis, trakeitis (radang tenggorok).","kontraindikasi":"","perhatian":"","efeksamping":"Nyeri lambung, gangguan saluran pencernaan.","indeksamanwanitahamil":"","kemasan":"Kapsul 375 mg x 100 biji.","dosis":"Dewasa : diawali dengan 3 kali sehari 2 kapsul, kemudian kurangi sampai 1 kapsul 4 kali sehari.","penyajian":"Dikonsumsi bersamaan dengan makanan","pabrik":"PT.  Pharma Healthcare","id":"5325","category_id":"3"}
