{"name":"BEXCE CAPLET","harga":"  Rp. 172.447/ kemasan","golongan":"http://medicastore.com/image_banner/obat_bebas.gif","kandungan":"Per kaplet : Vit B1 15 mg, vit B2 10 mg, vit B6 5 mg, vit B12 10 mcg, vit C 500 mg, Ca pantothenate 20 mg, nicotinamide 100 mg.","indikasi":"Kekurangan Vitamin B komplek dan Vitamin C.","kontraindikasi":"","perhatian":"","efeksamping":"","indeksamanwanitahamil":"","kemasan":"Kaplet 10 x 10 biji.","dosis":"1 kaplet sehari.","penyajian":"Dikonsumsi bersamaan dengan makanan atau tidak","pabrik":"Tempo Scan Pacific.","id":"665","category_id":"11"}
