{"name":"SILEX SYRUP","harga":"  Rp. 39.216/ kemasan","golongan":"http://medicastore.com/image_banner/obat_bebas_terbatas.gif","kandungan":"Per 5 mL : Guaifenesin 37.5 mg, thyme extr 250 mg, extr primulae 50 mg, extr althaea 175 mg, extr droserae 25 mg, extr serpylli 175 mg, eucalyptus oil 0.5 mg, anise oil 1.25 mg. / Guaifenesin 37,5 mg, Ekstrak Thymi 250 mg, Ekstrak Primulae 50 mg, Ekstrak Althaea 175 mg, Ekstrak Droserae 25 mg, Ekstrak Serpylli 175 mg, Minyak Eucalyptus 0,5 mg, Minyak Anisi 1,25 mg.","indikasi":"Batuk akibat bronkhitis, flu, faringitis, batuk rejan, batuk pada perokok.","kontraindikasi":"","perhatian":"","efeksamping":"","indeksamanwanitahamil":"","kemasan":"Sirup 100 mL.","dosis":"Dewasa : 3-4 kali sehari 15 mL. Anak-anak : 3-4 kali sehari 5 mL.","penyajian":"Tak ada pilihan","pabrik":"Darya-Varia.","id":"6833","category_id":"3"}
