{"name":"NEUROCET INFUS","harga":"  Rp. 146.410/ kemasan","golongan":"http://medicastore.com/image_banner/obat_keras_dan_psikotropika.gif","kandungan":"Piracetam.","indikasi":"Pengobatan infarksi serebral.","kontraindikasi":"Insufisiensi ginjal berat (bersihan kreatinin kurang dari 20 mL/menit).","perhatian":"Hamil, menyusui, kerusakan ginjal. Penghentian pengobatan secara tiba-tiba. Interaksi obat : ekstrak tiroid.","efeksamping":"Cepat marah, gangguan tidur, keresahan, kegugupan, kegelisahan, kelelahan, ketagihan tidur, gangguan lambung-usus.","indeksamanwanitahamil":"","kemasan":"Infus 12 g/60 ml x 1's","dosis":"Kasus berat : infus continu sampai dengan 12 gram/hari.","penyajian":"Tak ada pilihan","pabrik":"Hexpharm","id":"7575","category_id":"4"}
