{"name":"FLAMERGI TETES MATA","harga":"  Rp. 20.376/ kemasan","golongan":"http://medicastore.com/image_banner/obat_keras_dan_psikotropika.gif","kandungan":"Komposisi: Naphazoline hydrochloride 0,025%, pheniramine maleate 0,3%.","indikasi":"Menghilangkan kemerahan pada mata karena iritasi atau kongesti dan kondisi alergi atau inflamasi mata.","kontraindikasi":"Glaukoma sudut sempit.","perhatian":"Bayi dan anak,pemberian bersamaan dengan monoamine oxidase inhibitor.","efeksamping":"Dilatasi pupil, peningkatan tekanan intraokular.","indeksamanwanitahamil":"","kemasan":"Tetes mata 5 mL.","dosis":"1 - 2 tetes tiap 3 - 4 jam.","penyajian":"Tak ada pilihan","pabrik":"Sanbe Farma.","id":"8483","category_id":"13"}
