{"name":"BUGARET CAPLET","harga":"  Rp. 71.148/ kemasan","golongan":"http://medicastore.com/image_banner/obat_bebas_terbatas.gif","kandungan":"Vitamin E 30 iu, Vitamin C 750 mg, Asam folat 400 mcg, Vitamin B1 15 mg, Vitamin B2 15 mg, Niasin 100 mg, Vitamin B6 20 mg, Vitamin B12 12 mcg, Ca pantotenat 20 mg, Zn 22,5 mg.","indikasi":"Kekurangan vitamin & Zn.","kontraindikasi":"","perhatian":"","efeksamping":"","indeksamanwanitahamil":"","kemasan":"Kaptab 50 biji.","dosis":"1 tablet sehari.","penyajian":"Dikonsumsi bersamaan dengan makanan","pabrik":"Mecosin Indonesia.","id":"861","category_id":"11"}
