{"name":"DAIVONEX SALEP KULIT","harga":"  Rp. 290.400/ kemasan","golongan":"http://medicastore.com/image_banner/obat_keras_dan_psikotropika.gif","kandungan":"Calcipotriol / Kalsipotriol.","indikasi":"Psoriasis vulgaris.","kontraindikasi":"Hipersensitif.","perhatian":"- Tidak digunakan diwajah.- Basuh tangan setelah penggunaan.Interaksi Obat:Hindari terapi bersama dengan preparat topikal yang mengandung asam salisilat.","efeksamping":"Iritasi lokal transien, dermatitis pada wajah.","indeksamanwanitahamil":"","kemasan":"Salep 0,05% x 30 gram","dosis":"2 kali sehari, dioleskan tipis-tipis. Dosis mingguan maksimal: 100 gram.","penyajian":"Tak ada pilihan","pabrik":"Parazelsus Indonesia/LEO Pharma","id":"8836","category_id":"15"}
