{"name":"SETROVEL AMPUL","harga":"  Rp. 605.000/ kemasan","golongan":"http://medicastore.com/image_banner/obat_keras_dan_psikotropika.gif","kandungan":"Komposisi : Setiap mL Setrovel injeksi mengandung 1 mg Tropisetron HCl","indikasi":"Pencegahan mual dan muntah pada pasien kemoterapi kanker, radio terapi dan post operasi.","kontraindikasi":"Pada pasien yang hipersensitif terhadap tropisetron dan komponen lain dalam setrovel. Setrovel tidak boleh diberikan pada ibu hamil.","perhatian":"","efeksamping":"Sakit kepala, konstipasi, fatigue, gangguan pencernaan seperti sakit perut dan diare.","indeksamanwanitahamil":"","kemasan":"Box 10 Ampul @ 5 mL","dosis":"Dewasa : 5 mg per hari selama 6 hari, diberikan intra venna sehari sebelum kemoterapi kanker bersamaan dengan infus atau injeksi, diikuti dengan pemberian oral pada hari ke-2 sampai hari ke-6.Anak - anak : pada anak - anak usia lebih dari 2 tahun dosis 0,2 mg per kilo gram Berat Badan sampai dosis maksimum 5 mg per hari.Setrovel dapat diberikan dalam bentuk larutan minum yang dicampurkan ke dalam orange juice maupun cola dan sebaiknya di berikan pada pagi hari, 1 jam sebelum makan.","penyajian":"Tak ada pilihan","pabrik":"Novell Pharmaceutical Laboratories.","id":"9447","category_id":"1"}
